factual_scene_graph/__init__.py
factual_scene_graph/utils.py
factual_scene_graph/evaluation/__init__.py
factual_scene_graph/evaluation/evaluator.py
factual_scene_graph/evaluation/set_match_evaluation.py
factual_scene_graph/evaluation/soft_spice_evaluation.py
factual_scene_graph/evaluation/spice_evaluation.py
factual_scene_graph/evaluation/synonym_dictionary.py
factual_scene_graph/evaluation/resources/__init__.py
factual_scene_graph/evaluation/resources/english.exceptions
factual_scene_graph/evaluation/resources/english.synsets
factual_scene_graph/parser/__init__.py
factual_scene_graph/parser/scene_graph_parser.py
FactualSceneGraph-0.7.3.dist-info/METADATA
FactualSceneGraph-0.7.3.dist-info/WHEEL
FactualSceneGraph-0.7.3.dist-info/top_level.txt
FactualSceneGraph-0.7.3.dist-info/RECORD
