Metadata-Version: 2.1
Name: FactualSceneGraph
Version: 0.7.3
Summary: A package for scene graph parsing and evaluation with multi-sentence support
Home-page: https://github.com/zhuang-li/FACTUAL
Author: Zhuang Li
Author-email: lizhuang144@gmail.com
License: UNKNOWN
Platform: UNKNOWN
Classifier: Development Status :: 3 - Alpha
Classifier: Intended Audience :: Developers
Classifier: License :: OSI Approved :: MIT License
Classifier: Programming Language :: Python :: 3
Classifier: Programming Language :: Python :: 3.7
Classifier: Programming Language :: Python :: 3.8
Classifier: Operating System :: OS Independent
Requires-Dist: torch
Requires-Dist: transformers
Requires-Dist: tqdm
Requires-Dist: nltk
Requires-Dist: spacy
Requires-Dist: sentence-transformers
Requires-Dist: pandas
Requires-Dist: numpy
Requires-Dist: tabulate
Requires-Dist: discosg
